loadscompare/__init__.py
loadscompare/compare.py
loadscompare/plotting.py
loadscompare/graphics/LK_logo2.png
loadskernel/__init__.py
loadskernel/atmosphere.py
loadskernel/auxiliary_output.py
loadskernel/build_aero_functions.py
loadskernel/build_splinegrid.py
loadskernel/gather_loads.py
loadskernel/grid_trafo.py
loadskernel/integrate.py
loadskernel/interpolate.py
loadskernel/jcl_helper.py
loadskernel/model.py
loadskernel/plotting_extra.py
loadskernel/plotting_standard.py
loadskernel/post_processing.py
loadskernel/program_flow.py
loadskernel/solution_sequences.py
loadskernel/solution_tools.py
loadskernel/spline_functions.py
loadskernel/spline_rules.py
loadskernel/trim_conditions.py
loadskernel/units.py
loadskernel/cfd_interfaces/__init__.py
loadskernel/cfd_interfaces/meshdefo.py
loadskernel/cfd_interfaces/mpi_helper.py
loadskernel/cfd_interfaces/su2_interface.py
loadskernel/cfd_interfaces/tau_interface.py
loadskernel/engine_interfaces/__init__.py
loadskernel/engine_interfaces/engine.py
loadskernel/engine_interfaces/propeller.py
loadskernel/equations/__init__.py
loadskernel/equations/cfd.py
loadskernel/equations/common.py
loadskernel/equations/frequency_domain.py
loadskernel/equations/landing.py
loadskernel/equations/nonlin_steady.py
loadskernel/equations/state_space.py
loadskernel/equations/steady.py
loadskernel/equations/unsteady.py
loadskernel/fem_interfaces/__init__.py
loadskernel/fem_interfaces/b2000_interface.py
loadskernel/fem_interfaces/cofe_interface.py
loadskernel/fem_interfaces/fem_helper.py
loadskernel/fem_interfaces/nastran_f06_interface.py
loadskernel/fem_interfaces/nastran_interface.py
loadskernel/graphics/LK_logo2.png
loadskernel/io_functions/__init__.py
loadskernel/io_functions/bdf_cards.py
loadskernel/io_functions/data_handling.py
loadskernel/io_functions/read_b2000.py
loadskernel/io_functions/read_bdf.py
loadskernel/io_functions/read_cfdgrids.py
loadskernel/io_functions/read_h5.py
loadskernel/io_functions/read_mona.py
LoadsKernel-2025.1.dist-info/AUTHORS.md
LoadsKernel-2025.1.dist-info/LICENSE
LoadsKernel-2025.1.dist-info/METADATA
LoadsKernel-2025.1.dist-info/WHEEL
LoadsKernel-2025.1.dist-info/entry_points.txt
LoadsKernel-2025.1.dist-info/top_level.txt
LoadsKernel-2025.1.dist-info/RECORD
