Metadata-Version: 2.1
Name: LoadsKernel
Version: 2025.1
Summary: The Loads Kernel Software allows for the calculation of quasi-steady and dynamic maneuver loads,
Home-page: https://github.com/DLR-AE/LoadsKernel
Author: Arne Voß
Author-email: arne.voss@dlr.de
License: BSD 3-Clause License
Requires-Python: >=3.10
License-File: LICENSE
License-File: AUTHORS.md
Requires-Dist: PanelAero
Requires-Dist: matplotlib
Requires-Dist: numpy
Requires-Dist: scipy
Requires-Dist: psutil
Requires-Dist: h5py
Requires-Dist: tables
Requires-Dist: pyyaml
Requires-Dist: pandas
Provides-Extra: extras
Requires-Dist: mpi4py; extra == "extras"
Requires-Dist: mayavi; extra == "extras"
Requires-Dist: traits; extra == "extras"
Requires-Dist: traitsui; extra == "extras"
Requires-Dist: pyface; extra == "extras"
Requires-Dist: jupyter; extra == "extras"
Requires-Dist: pyiges; extra == "extras"
Provides-Extra: difficult
Requires-Dist: pyfmi; extra == "difficult"
Provides-Extra: test
Requires-Dist: pytest; extra == "test"
Requires-Dist: pytest-cov; extra == "test"
Requires-Dist: jupyter-book; extra == "test"
Requires-Dist: flake8; extra == "test"
Requires-Dist: pylint; extra == "test"
